[
  {
    "content": "Ampliando os Limites da Terapia Cognitiva",
    "author": "Jeremy D. Safran"
  },
  {
    "content": "Aprendendo a Terapia Cognitivo-Comportamental - Um Guia Ilustrado",
    "author": "Jesse H. Wright; Monica R. Basco; Michael E. Thase"
  },
  {
    "content": "Como lidar com as Preocupações - sete passos para impedir que elas paralisem você",
    "author": "Robert L. Leahy"
  },
  {
    "content": "Dieta Definitiva de Beck: Treine seu Cérebro para Pensar como uma Pessoa Magra, A",
    "author": "BECK, J.S."
  },
  {
    "content": "DOMINANDO O TDAH ADULTO - Guia do Terapeuta",
    "author": "Steven A. Safren, Susan Sprich, Carol A. Perlman e Michael W. Otto"
  },
  {
    "content": "Esquemas de Terapia: Guia Prático",
    "author": "YOUNG, J.E."
  },
  {
    "content": "Estratégias Cognitivo-Comportamentais de Intervenção em Situações de Crise (2.ed.)",
    "author": "DATTILIO, F.M.; FREEMAN, A. &, COLS."
  },
  {
    "content": "Guia do terapeuta para os bons pensamentos-bons sentimentos",
    "author": "Paul Stallard"
  },
  {
    "content": "Manual de Técnicas em Terapia Cognitiva",
    "author": "MCMULLIN, R.E."
  },
  {
    "content": "A Mente Vencendo o Humor: Mude como Você se Sente, Mudando o Modo como Você Pensa",
    "author": "GREENBERGER, D.; PADESKY, C.A."
  },
  {
    "content": "Manual de Terapias Cognitivo-Comportamentais",
    "author": "Keith S. Dobson & cols."
  },
  {
    "content": "O Poder Integrador da Terapia Cognitiva",
    "author": "BECK, A.T.; ALFORD, B.A."
  },
  {
    "content": "Pense Magro - A Dieta Definitiva de Beck",
    "author": "Judith S. Beck"
  },
  {
    "content": "A Prática Cognitiva na Infância",
    "author": "Renato Maiato Caminha e Marina Gusmão Caminha"
  },
  {
    "content": "Processos Humanos de Mudança: As Bases Científicas da Psicoterapia",
    "author": "Michael Mahoney"
  },
  {
    "content": "Psicoterapias Cognitiva e Construtivista",
    "author": "Cristiano Nabuco de Abreu, Miréia Roso e Cols"
  },
  {
    "content": "Psicoterapias Cognitivo–Comportamentais: Um Díalogo com a Psiquiatria",
    "author": "Bernard Range"
  },
  {
    "content": "Superando a Resistência em Terapia Cognitiva",
    "author": "Robert L. Leahy"
  },
  {
    "content": "Técnicas de Terapia Cognitiva - Manual do terapeuta",
    "author": "Robert L. Leahy"
  },
  {
    "content": "A Prática Clínica de Terapia Cognitiva com Crianças e Adolescentes",
    "author": "Robert D. Friedberg e Jessica M. McClure"
  }
]
